{"name": "Cargo wagon", "recipe": {"normal": {"Recipe": {"source": [{"name": "Time", "amount": "1", "url": "/Time", "img": "/images/Time_icon.png"}, {"name": "Iron gear wheel", "amount": "10", "url": "/Iron_gear_wheel", "img": "/images/Iron_gear_wheel.png"}, {"name": "Iron plate", "amount": "20", "url": "/Iron_plate", "img": "/images/Iron_plate.png"}, {"name": "Steel plate", "amount": "20", "url": "/Steel_plate", "img": "/images/Steel_plate.png"}], "result": [{"name": "Cargo wagon", "amount": "1", "url": "/Cargo_wagon", "img": "/images/Cargo_wagon.png"}]}, "Total raw": {"result": [{"name": "Time", "amount": "6", "url": "/Time", "img": "/images/Time_icon.png"}, {"name": "Iron plate", "amount": "40", "url": "/Iron_plate", "img": "/images/Iron_plate.png"}, {"name": "Steel plate", "amount": "20", "url": "/Steel_plate", "img": "/images/Steel_plate.png"}]}}, "expensive": {"Recipe": {"source": [{"name": "Time", "amount": "1", "url": "/Time", "img": "/images/Time_icon.png"}, {"name": "Iron gear wheel", "amount": "10", "url": "/Iron_gear_wheel", "img": "/images/Iron_gear_wheel.png"}, {"name": "Iron plate", "amount": "20", "url": "/Iron_plate", "img": "/images/Iron_plate.png"}, {"name": "Steel plate", "amount": "20", "url": "/Steel_plate", "img": "/images/Steel_plate.png"}], "result": [{"name": "Cargo wagon", "amount": "1", "url": "/Cargo_wagon", "img": "/images/Cargo_wagon.png"}]}, "Total raw": {"result": [{"name": "Time", "amount": "6", "url": "/Time", "img": "/images/Time_icon.png"}, {"name": "Iron plate", "amount": "60", "url": "/Iron_plate", "img": "/images/Iron_plate.png"}, {"name": "Steel plate", "amount": "20", "url": "/Steel_plate", "img": "/images/Steel_plate.png"}]}}}, "Storage size": "40", "Health": "600", "Stack size": "5", "Dimensions": "2x6", "Internal name": "cargo-wagon", "Prototype type": "cargo-wagon", "Required technologies": [{"name": "Railway (research)", "url": "/Railway_(research)", "img": "/images/thumb/Railway_%28research%29.png/32px-Railway_%28research%29.png"}], "Produced by": [{"name": "Manual crafting", "url": "/Manual_crafting", "img": "/images/Hand_icon.png"}, {"name": "Assembling machine 2", "url": "/Assembling_machine_2", "img": "/images/Assembling_machine_2.png"}, {"name": "Assembling machine 3", "url": "/Assembling_machine_3", "img": "/images/Assembling_machine_3.png"}]}