{"name": "Logistic robot", "recipe": {"normal": {"Recipe": {"source": [{"name": "Time", "amount": "0.5", "url": "/Time", "img": "/images/Time_icon.png"}, {"name": "Advanced circuit", "amount": "2", "url": "/Advanced_circuit", "img": "/images/Advanced_circuit.png"}, {"name": "Flying robot frame", "amount": "1", "url": "/Flying_robot_frame", "img": "/images/Flying_robot_frame.png"}], "result": [{"name": "Logistic robot", "amount": "1", "url": "/Logistic_robot", "img": "/images/Logistic_robot.png"}]}, "Total raw": {"result": [{"name": "Time", "amount": "43.25", "url": "/Time", "img": "/images/Time_icon.png"}, {"name": "Battery", "amount": "2", "url": "/Battery", "img": "/images/Battery.png"}, {"name": "Copper plate", "amount": "14.5", "url": "/Copper_plate", "img": "/images/Copper_plate.png"}, {"name": "Electric engine unit", "amount": "1", "url": "/Electric_engine_unit", "img": "/images/Electric_engine_unit.png"}, {"name": "Iron plate", "amount": "7", "url": "/Iron_plate", "img": "/images/Iron_plate.png"}, {"name": "Plastic bar", "amount": "4", "url": "/Plastic_bar", "img": "/images/Plastic_bar.png"}, {"name": "Steel plate", "amount": "1", "url": "/Steel_plate", "img": "/images/Steel_plate.png"}]}}, "expensive": {"Recipe": {"source": [{"name": "Time", "amount": "0.5", "url": "/Time", "img": "/images/Time_icon.png"}, {"name": "Advanced circuit", "amount": "2", "url": "/Advanced_circuit", "img": "/images/Advanced_circuit.png"}, {"name": "Flying robot frame", "amount": "1", "url": "/Flying_robot_frame", "img": "/images/Flying_robot_frame.png"}], "result": [{"name": "Logistic robot", "amount": "1", "url": "/Logistic_robot", "img": "/images/Logistic_robot.png"}]}, "Total raw": {"result": [{"name": "Time", "amount": "57.5", "url": "/Time", "img": "/images/Time_icon.png"}, {"name": "Battery", "amount": "2", "url": "/Battery", "img": "/images/Battery.png"}, {"name": "Copper plate", "amount": "43", "url": "/Copper_plate", "img": "/images/Copper_plate.png"}, {"name": "Electric engine unit", "amount": "1", "url": "/Electric_engine_unit", "img": "/images/Electric_engine_unit.png"}, {"name": "Iron plate", "amount": "14", "url": "/Iron_plate", "img": "/images/Iron_plate.png"}, {"name": "Plastic bar", "amount": "8", "url": "/Plastic_bar", "img": "/images/Plastic_bar.png"}, {"name": "Steel plate", "amount": "1", "url": "/Steel_plate", "img": "/images/Steel_plate.png"}]}}}, "Health": "100", "Stack size": "50", "Internal name": "logistic-robot", "Prototype type": "logistic-robot", "Required technologies": [{"name": "Logistic robotics (research)", "url": "/Logistic_robotics_(research)", "img": "/images/thumb/Logistic_robotics_%28research%29.png/32px-Logistic_robotics_%28research%29.png"}], "Produced by": [{"name": "Manual crafting", "url": "/Manual_crafting", "img": "/images/Hand_icon.png"}, {"name": "Assembling machine 1", "url": "/Assembling_machine_1", "img": "/images/Assembling_machine_1.png"}, {"name": "Assembling machine 2", "url": "/Assembling_machine_2", "img": "/images/Assembling_machine_2.png"}, {"name": "Assembling machine 3", "url": "/Assembling_machine_3", "img": "/images/Assembling_machine_3.png"}]}